[
	{
		"__TYPE__": "SharedSliceContent",
		"variation": "default",
		"primary": {
			"section_title": {
				"__TYPE__": "FieldContent",
				"value": "independent",
				"type": "Text"
			},
			"section_id": {
				"__TYPE__": "FieldContent",
				"value": "grew",
				"type": "Text"
			}
		},
		"items": [
			{
				"__TYPE__": "GroupItemContent",
				"value": [
					[
						"project",
						{
							"__TYPE__": "LinkContent",
							"value": {
								"__TYPE__": "DocumentLink",
								"id": "mock_document_id"
							}
						}
					]
				]
			}
		]
	}
]